KuiToi/__init__.py
KuiToi/__version__.py
KuiToi-0.1.0.dist-info/LICENSE
KuiToi-0.1.0.dist-info/METADATA
KuiToi-0.1.0.dist-info/WHEEL
KuiToi-0.1.0.dist-info/top_level.txt
KuiToi-0.1.0.dist-info/RECORD
